{"games":[{"rounds":[{"playerMove":0,"result":1},{"playerMove":0,"result":-1},{"playerMove":0,"result":-1},{"playerMove":0,"result":0},{"playerMove":0,"result":-1},{"playerMove":0,"result":-1},{"playerMove":0,"result":1},{"playerMove":0,"result":1},{"playerMove":0,"result":-1},{"playerMove":0,"result":-1},{"playerMove":0,"result":1},{"playerMove":0,"result":-1},{"playerMove":0,"result":0},{"playerMove":0,"result":1},{"playerMove":0,"result":1},{"playerMove":1,"result":0},{"playerMove":2,"result":1},{"playerMove":0,"result":-1},{"playerMove":1,"result":-1},{"playerMove":0,"result":-1},{"playerMove":1,"result":0},{"playerMove":2,"result":0},{"playerMove":1,"result":0},{"playerMove":0,"result":1},{"playerMove":2,"result":1},{"playerMove":1,"result":0},{"playerMove":0,"result":0},{"playerMove":2,"result":-1},{"playerMove":1,"result":0},{"playerMove":0,"result":0},{"playerMove":2,"result":0},{"playerMove":1,"result":-1},{"playerMove":0,"result":-1},{"playerMove":2,"result":0},{"playerMove":1,"result":-1},{"playerMove":0,"result":-1},{"playerMove":2,"result":1},{"playerMove":1,"result":-1},{"playerMove":0,"result":-1},{"playerMove":2,"result":1},{"playerMove":1,"result":-1},{"playerMove":0,"result":-1},{"playerMove":2,"result":-1},{"playerMove":1,"result":0},{"playerMove":0,"result":0},{"playerMove":2,"result":-1},{"playerMove":1,"result":1},{"playerMove":0,"result":-1},{"playerMove":2,"result":0},{"playerMove":1,"result":-1},{"playerMove":0,"result":-1},{"playerMove":2,"result":0},{"playerMove":1,"result":1},{"playerMove":0,"result":-1},{"playerMove":2,"result":1},{"playerMove":1,"result":0},{"playerMove":0,"result":0},{"playerMove":2,"result":1},{"playerMove":1,"result":-1},{"playerMove":0,"result":-1},{"playerMove":2,"result":0},{"playerMove":1,"result":-1},{"playerMove":0,"result":-1},{"playerMove":2,"result":-1},{"playerMove":1,"result":-1},{"playerMove":0,"result":-1},{"playerMove":2,"result":1},{"playerMove":1,"result":-1},{"playerMove":0,"result":-1},{"playerMove":2,"result":1},{"playerMove":1,"result":-1},{"playerMove":0,"result":0},{"playerMove":2,"result":-1},{"playerMove":1,"result":-1},{"playerMove":0,"result":-1},{"playerMove":2,"result":-1},{"playerMove":1,"result":-1},{"playerMove":0,"result":-1},{"playerMove":2,"result":-1},{"playerMove":1,"result":1},{"playerMove":0,"result":-1},{"playerMove":2,"result":-1},{"playerMove":1,"result":-1},{"playerMove":0,"result":-1},{"playerMove":2,"result":-1},{"playerMove":1,"result":-1},{"playerMove":0,"result":-1},{"playerMove":2,"result":-1},{"playerMove":1,"result":-1},{"playerMove":0,"result":-1},{"playerMove":2,"result":0},{"playerMove":1,"result":0},{"playerMove":0,"result":-1},{"playerMove":2,"result":-1},{"playerMove":1,"result":-1},{"playerMove":0,"result":-1},{"playerMove":2,"result":-1},{"playerMove":1,"result":-1},{"playerMove":0,"result":-1},{"playerMove":2,"result":1},{"playerMove":1,"result":-1},{"playerMove":0,"result":-1},{"playerMove":2,"result":-1},{"playerMove":1,"result":-1},{"playerMove":0,"result":-1},{"playerMove":2,"result":-1},{"playerMove":1,"result":-1},{"playerMove":0,"result":-1},{"playerMove":2,"result":-1},{"playerMove":1,"result":-1},{"playerMove":0,"result":-1},{"playerMove":2,"result":-1},{"playerMove":1,"result":-1},{"playerMove":0,"result":-1},{"playerMove":2,"result":-1},{"playerMove":1,"result":-1},{"playerMove":0,"result":-1},{"playerMove":2,"result":0},{"playerMove":1,"result":-1},{"playerMove":0,"result":-1},{"playerMove":2,"result":-1},{"playerMove":1,"result":-1},{"playerMove":0,"result":-1},{"playerMove":2,"result":1},{"playerMove":1,"result":-1},{"playerMove":0,"result":-1},{"playerMove":2,"result":1},{"playerMove":1,"result":-1},{"playerMove":0,"result":-1},{"playerMove":2,"result":1},{"playerMove":1,"result":-1},{"playerMove":0,"result":-1},{"playerMove":2,"result":1},{"playerMove":1,"result":-1},{"playerMove":0,"result":-1},{"playerMove":2,"result":-1},{"playerMove":1,"result":-1},{"playerMove":0,"result":-1},{"playerMove":2,"result":-1},{"playerMove":1,"result":-1},{"playerMove":0,"result":-1},{"playerMove":2,"result":-1},{"playerMove":1,"result":0},{"playerMove":0,"result":0},{"playerMove":2,"result":-1},{"playerMove":1,"result":-1},{"playerMove":0,"result":-1},{"playerMove":2,"result":-1},{"playerMove":1,"result":-1},{"playerMove":0,"result":1},{"playerMove":2,"result":1},{"playerMove":1,"result":-1},{"playerMove":0,"result":-1},{"playerMove":2,"result":-1},{"playerMove":1,"result":-1},{"playerMove":0,"result":-1},{"playerMove":2,"result":-1},{"playerMove":1,"result":-1},{"playerMove":0,"result":-1},{"playerMove":2,"result":0},{"playerMove":1,"result":1},{"playerMove":0,"result":-1},{"playerMove":2,"result":-1},{"playerMove":1,"result":1},{"playerMove":0,"result":-1},{"playerMove":2,"result":-1},{"playerMove":1,"result":-1},{"playerMove":0,"result":-1},{"playerMove":2,"result":-1},{"playerMove":1,"result":-1},{"playerMove":0,"result":-1},{"playerMove":2,"result":0},{"playerMove":1,"result":-1},{"playerMove":0,"result":0},{"playerMove":2,"result":-1},{"playerMove":1,"result":-1},{"playerMove":0,"result":-1},{"playerMove":2,"result":1},{"playerMove":1,"result":0},{"playerMove":0,"result":-1},{"playerMove":2,"result":-1},{"playerMove":1,"result":-1},{"playerMove":0,"result":-1},{"playerMove":2,"result":-1},{"playerMove":1,"result":-1},{"playerMove":0,"result":-1},{"playerMove":2,"result":-1},{"playerMove":1,"result":-1},{"playerMove":0,"result":-1},{"playerMove":2,"result":-1},{"playerMove":1,"result":-1},{"playerMove":0,"result":-1},{"playerMove":2,"result":-1},{"playerMove":1,"result":-1},{"playerMove":0,"result":-1},{"playerMove":2,"result":-1},{"playerMove":1,"result":-1},{"playerMove":0,"result":-1},{"playerMove":2,"result":-1},{"playerMove":1,"result":-1},{"playerMove":0,"result":-1},{"playerMove":2,"result":-1},{"playerMove":1,"result":-1},{"playerMove":0,"result":-1},{"playerMove":2,"result":-1},{"playerMove":1,"result":-1},{"playerMove":0,"result":-1},{"playerMove":2,"result":-1},{"playerMove":1,"result":-1},{"playerMove":0,"result":-1},{"playerMove":2,"result":-1},{"playerMove":1,"result":-1},{"playerMove":0,"result":-1},{"playerMove":2,"result":-1},{"playerMove":1,"result":-1},{"playerMove":0,"result":-1},{"playerMove":2,"result":-1},{"playerMove":1,"result":-1},{"playerMove":0,"result":-1},{"playerMove":2,"result":-1},{"playerMove":1,"result":-1},{"playerMove":0,"result":-1},{"playerMove":2,"result":-1},{"playerMove":1,"result":1},{"playerMove":0,"result":-1},{"playerMove":2,"result":-1},{"playerMove":1,"result":-1},{"playerMove":0,"result":-1},{"playerMove":2,"result":-1},{"playerMove":1,"result":-1},{"playerMove":0,"result":-1},{"playerMove":2,"result":-1},{"playerMove":1,"result":-1},{"playerMove":0,"result":-1},{"playerMove":2,"result":-1},{"playerMove":1,"result":-1},{"playerMove":0,"result":-1},{"playerMove":2,"result":-1},{"playerMove":1,"result":-1},{"playerMove":0,"result":-1},{"playerMove":2,"result":-1},{"playerMove":1,"result":-1},{"playerMove":0,"result":-1},{"playerMove":2,"result":-1},{"playerMove":1,"result":-1},{"playerMove":0,"result":-1},{"playerMove":2,"result":-1},{"playerMove":1,"result":-1},{"playerMove":0,"result":-1},{"playerMove":2,"result":-1},{"playerMove":1,"result":-1},{"playerMove":0,"result":-1},{"playerMove":2,"result":-1},{"playerMove":1,"result":-1},{"playerMove":0,"result":-1},{"playerMove":2,"result":-1},{"playerMove":1,"result":-1},{"playerMove":0,"result":-1},{"playerMove":2,"result":-1},{"playerMove":1,"result":-1},{"playerMove":0,"result":-1},{"playerMove":2,"result":1},{"playerMove":1,"result":-1},{"playerMove":0,"result":-1},{"playerMove":2,"result":-1},{"playerMove":1,"result":-1},{"playerMove":0,"result":-1},{"playerMove":2,"result":-1},{"playerMove":1,"result":-1},{"playerMove":0,"result":-1},{"playerMove":2,"result":-1},{"playerMove":1,"result":-1},{"playerMove":0,"result":-1},{"playerMove":2,"result":-1},{"playerMove":1,"result":1},{"playerMove":0,"result":-1},{"playerMove":2,"result":1},{"playerMove":1,"result":-1},{"playerMove":0,"result":-1},{"playerMove":2,"result":-1},{"playerMove":1,"result":-1},{"playerMove":0,"result":-1},{"playerMove":2,"result":0},{"playerMove":1,"result":-1},{"playerMove":0,"result":-1},{"playerMove":2,"result":-1},{"playerMove":1,"result":-1},{"playerMove":0,"result":-1},{"playerMove":2,"result":-1},{"playerMove":1,"result":-1},{"playerMove":0,"result":-1},{"playerMove":2,"result":-1},{"playerMove":1,"result":-1},{"playerMove":0,"result":-1},{"playerMove":2,"result":-1},{"playerMove":1,"result":-1},{"playerMove":0,"result":-1},{"playerMove":2,"result":1},{"playerMove":1,"result":-1},{"playerMove":0,"result":-1},{"playerMove":2,"result":-1},{"playerMove":1,"result":-1},{"playerMove":0,"result":-1},{"playerMove":2,"result":0},{"playerMove":1,"result":-1},{"playerMove":0,"result":-1},{"playerMove":2,"result":-1},{"playerMove":1,"result":-1},{"playerMove":0,"result":-1},{"playerMove":2,"result":-1},{"playerMove":1,"result":-1},{"playerMove":0,"result":-1},{"playerMove":2,"result":-1},{"playerMove":1,"result":-1},{"playerMove":0,"result":-1},{"playerMove":2,"result":-1},{"playerMove":1,"result":-1},{"playerMove":0,"result":-1},{"playerMove":2,"result":-1},{"playerMove":1,"result":-1},{"playerMove":0,"result":-1},{"playerMove":2,"result":1},{"playerMove":1,"result":-1},{"playerMove":0,"result":-1},{"playerMove":2,"result":-1},{"playerMove":1,"result":-1},{"playerMove":0,"result":-1},{"playerMove":2,"result":1},{"playerMove":1,"result":-1},{"playerMove":0,"result":-1},{"playerMove":2,"result":-1},{"playerMove":1,"result":-1},{"playerMove":0,"result":-1},{"playerMove":2,"result":1},{"playerMove":1,"result":-1},{"playerMove":0,"result":-1},{"playerMove":2,"result":-1},{"playerMove":1,"result":-1},{"playerMove":0,"result":-1},{"playerMove":2,"result":-1},{"playerMove":1,"result":-1},{"playerMove":0,"result":-1},{"playerMove":2,"result":-1},{"playerMove":1,"result":-1},{"playerMove":0,"result":-1},{"playerMove":2,"result":-1},{"playerMove":1,"result":-1},{"playerMove":0,"result":-1},{"playerMove":2,"result":-1},{"playerMove":1,"result":-1},{"playerMove":0,"result":-1},{"playerMove":2,"result":-1},{"playerMove":1,"result":-1},{"playerMove":0,"result":-1},{"playerMove":2,"result":-1},{"playerMove":1,"result":-1},{"playerMove":0,"result":-1},{"playerMove":2,"result":-1},{"playerMove":1,"result":-1},{"playerMove":0,"result":-1},{"playerMove":2,"result":-1},{"playerMove":1,"result":-1},{"playerMove":0,"result":-1},{"playerMove":2,"result":-1},{"playerMove":1,"result":-1},{"playerMove":0,"result":-1},{"playerMove":2,"result":-1},{"playerMove":1,"result":-1},{"playerMove":0,"result":-1},{"playerMove":2,"result":-1},{"playerMove":1,"result":-1},{"playerMove":0,"result":-1},{"playerMove":2,"result":-1},{"playerMove":1,"result":-1},{"playerMove":0,"result":-1},{"playerMove":2,"result":-1},{"playerMove":1,"result":-1},{"playerMove":0,"result":-1},{"playerMove":2,"result":-1},{"playerMove":1,"result":-1},{"playerMove":0,"result":-1},{"playerMove":2,"result":-1},{"playerMove":1,"result":-1},{"playerMove":0,"result":-1},{"playerMove":2,"result":-1},{"playerMove":1,"result":-1},{"playerMove":0,"result":-1},{"playerMove":2,"result":-1},{"playerMove":1,"result":-1},{"playerMove":0,"result":-1},{"playerMove":2,"result":-1},{"playerMove":1,"result":-1},{"playerMove":0,"result":-1},{"playerMove":2,"result":-1},{"playerMove":1,"result":-1},{"playerMove":0,"result":-1},{"playerMove":2,"result":-1},{"playerMove":1,"result":-1},{"playerMove":0,"result":-1},{"playerMove":2,"result":-1},{"playerMove":1,"result":-1},{"playerMove":0,"result":-1},{"playerMove":2,"result":-1},{"playerMove":1,"result":-1},{"playerMove":0,"result":-1},{"playerMove":2,"result":-1},{"playerMove":1,"result":0},{"playerMove":0,"result":-1},{"playerMove":2,"result":-1},{"playerMove":1,"result":-1},{"playerMove":0,"result":-1},{"playerMove":2,"result":-1},{"playerMove":1,"result":-1},{"playerMove":0,"result":-1},{"playerMove":2,"result":1},{"playerMove":1,"result":-1},{"playerMove":0,"result":-1},{"playerMove":2,"result":-1},{"playerMove":1,"result":-1},{"playerMove":0,"result":-1},{"playerMove":2,"result":-1},{"playerMove":1,"result":-1},{"playerMove":0,"result":-1},{"playerMove":2,"result":-1},{"playerMove":1,"result":-1},{"playerMove":0,"result":-1},{"playerMove":2,"result":-1},{"playerMove":1,"result":-1},{"playerMove":0,"result":-1},{"playerMove":2,"result":-1},{"playerMove":1,"result":-1},{"playerMove":0,"result":-1},{"playerMove":2,"result":-1},{"playerMove":1,"result":-1},{"playerMove":0,"result":-1},{"playerMove":2,"result":-1},{"playerMove":1,"result":-1},{"playerMove":0,"result":-1},{"playerMove":2,"result":-1},{"playerMove":1,"result":-1},{"playerMove":0,"result":-1},{"playerMove":2,"result":-1},{"playerMove":1,"result":-1},{"playerMove":0,"result":-1},{"playerMove":2,"result":-1},{"playerMove":1,"result":-1},{"playerMove":0,"result":-1},{"playerMove":2,"result":-1},{"playerMove":1,"result":-1},{"playerMove":0,"result":-1},{"playerMove":2,"result":-1},{"playerMove":1,"result":-1},{"playerMove":0,"result":-1},{"playerMove":2,"result":-1},{"playerMove":1,"result":-1},{"playerMove":0,"result":-1},{"playerMove":2,"result":-1},{"playerMove":1,"result":-1},{"playerMove":0,"result":-1},{"playerMove":2,"result":-1},{"playerMove":1,"result":-1},{"playerMove":0,"result":-1},{"playerMove":2,"result":-1},{"playerMove":1,"result":-1},{"playerMove":0,"result":-1},{"playerMove":2,"result":-1},{"playerMove":1,"result":1},{"playerMove":0,"result":-1},{"playerMove":2,"result":-1},{"playerMove":1,"result":-1},{"playerMove":0,"result":-1},{"playerMove":2,"result":-1},{"playerMove":1,"result":-1},{"playerMove":0,"result":-1},{"playerMove":2,"result":-1},{"playerMove":1,"result":-1},{"playerMove":0,"result":-1},{"playerMove":2,"result":-1},{"playerMove":1,"result":-1},{"playerMove":0,"result":-1},{"playerMove":2,"result":-1},{"playerMove":1,"result":-1},{"playerMove":0,"result":-1},{"playerMove":2,"result":-1},{"playerMove":1,"result":-1},{"playerMove":0,"result":-1},{"playerMove":2,"result":-1},{"playerMove":1,"result":-1},{"playerMove":0,"result":-1},{"playerMove":2,"result":1},{"playerMove":1,"result":-1},{"playerMove":0,"result":-1},{"playerMove":2,"result":-1},{"playerMove":1,"result":-1},{"playerMove":0,"result":-1},{"playerMove":2,"result":-1},{"playerMove":1,"result":-1},{"playerMove":0,"result":1},{"playerMove":2,"result":-1},{"playerMove":1,"result":-1}],"stats":{"nOfLoses":428,"nOfRounds":500,"nOfTies":32,"nOfWins":32,"playerWinRate":0.08,"iaWinRate":0.856,"tieRate":0.064}},{"rounds":[{"playerMove":1,"result":0},{"playerMove":0,"result":-1},{"playerMove":2,"result":-1},{"playerMove":1,"result":1},{"playerMove":0,"result":0},{"playerMove":2,"result":1},{"playerMove":1,"result":-1},{"playerMove":0,"result":-1},{"playerMove":2,"result":-1},{"playerMove":1,"result":1},{"playerMove":0,"result":-1},{"playerMove":2,"result":-1},{"playerMove":1,"result":1},{"playerMove":0,"result":-1},{"playerMove":1,"result":-1},{"playerMove":0,"result":-1},{"playerMove":2,"result":-1},{"playerMove":2,"result":0},{"playerMove":1,"result":-1},{"playerMove":0,"result":0},{"playerMove":2,"result":1},{"playerMove":1,"result":-1},{"playerMove":0,"result":-1},{"playerMove":2,"result":-1},{"playerMove":1,"result":-1},{"playerMove":0,"result":-1},{"playerMove":2,"result":-1},{"playerMove":1,"result":0},{"playerMove":0,"result":0},{"playerMove":2,"result":-1},{"playerMove":1,"result":1},{"playerMove":0,"result":-1},{"playerMove":2,"result":-1},{"playerMove":1,"result":-1},{"playerMove":0,"result":-1},{"playerMove":2,"result":-1},{"playerMove":1,"result":1},{"playerMove":0,"result":-1},{"playerMove":2,"result":-1},{"playerMove":1,"result":-1},{"playerMove":0,"result":-1},{"playerMove":2,"result":0},{"playerMove":1,"result":-1},{"playerMove":0,"result":0},{"playerMove":2,"result":-1},{"playerMove":1,"result":-1},{"playerMove":0,"result":-1},{"playerMove":1,"result":1},{"playerMove":0,"result":0},{"playerMove":2,"result":0},{"playerMove":1,"result":-1},{"playerMove":0,"result":-1},{"playerMove":2,"result":0},{"playerMove":1,"result":-1},{"playerMove":0,"result":-1},{"playerMove":2,"result":1},{"playerMove":2,"result":0},{"playerMove":1,"result":-1},{"playerMove":0,"result":-1},{"playerMove":2,"result":-1},{"playerMove":1,"result":-1},{"playerMove":0,"result":-1},{"playerMove":1,"result":1},{"playerMove":0,"result":-1},{"playerMove":2,"result":1},{"playerMove":1,"result":0},{"playerMove":2,"result":-1},{"playerMove":0,"result":1},{"playerMove":1,"result":0},{"playerMove":2,"result":-1},{"playerMove":0,"result":1},{"playerMove":1,"result":-1},{"playerMove":2,"result":1},{"playerMove":0,"result":1},{"playerMove":0,"result":1},{"playerMove":1,"result":1},{"playerMove":2,"result":1},{"playerMove":0,"result":0},{"playerMove":1,"result":-1},{"playerMove":0,"result":-1},{"playerMove":1,"result":1},{"playerMove":0,"result":0},{"playerMove":2,"result":-1},{"playerMove":1,"result":0},{"playerMove":0,"result":-1},{"playerMove":2,"result":-1},{"playerMove":0,"result":-1},{"playerMove":0,"result":0},{"playerMove":2,"result":-1},{"playerMove":1,"result":1},{"playerMove":2,"result":1},{"playerMove":1,"result":1},{"playerMove":0,"result":-1},{"playerMove":1,"result":1},{"playerMove":2,"result":1},{"playerMove":0,"result":1},{"playerMove":1,"result":-1},{"playerMove":0,"result":-1},{"playerMove":2,"result":-1},{"playerMove":0,"result":0},{"playerMove":1,"result":1},{"playerMove":2,"result":-1},{"playerMove":1,"result":0},{"playerMove":1,"result":1},{"playerMove":2,"result":1},{"playerMove":1,"result":1},{"playerMove":2,"result":1},{"playerMove":0,"result":-1},{"playerMove":0,"result":0},{"playerMove":2,"result":-1},{"playerMove":1,"result":-1},{"playerMove":2,"result":0},{"playerMove":1,"result":1},{"playerMove":2,"result":-1},{"playerMove":1,"result":-1},{"playerMove":2,"result":1},{"playerMove":0,"result":1},{"playerMove":0,"result":0},{"playerMove":2,"result":-1},{"playerMove":0,"result":1},{"playerMove":2,"result":-1},{"playerMove":0,"result":1},{"playerMove":1,"result":1},{"playerMove":2,"result":-1},{"playerMove":1,"result":-1},{"playerMove":2,"result":-1},{"playerMove":1,"result":-1},{"playerMove":2,"result":-1},{"playerMove":0,"result":1},{"playerMove":2,"result":1},{"playerMove":0,"result":1},{"playerMove":2,"result":0},{"playerMove":1,"result":1},{"playerMove":1,"result":0},{"playerMove":2,"result":-1},{"playerMove":1,"result":1},{"playerMove":2,"result":1},{"playerMove":0,"result":1},{"playerMove":2,"result":-1},{"playerMove":0,"result":-1},{"playerMove":2,"result":-1},{"playerMove":1,"result":0},{"playerMove":0,"result":-1},{"playerMove":2,"result":-1},{"playerMove":1,"result":0},{"playerMove":0,"result":0},{"playerMove":2,"result":0},{"playerMove":1,"result":-1},{"playerMove":1,"result":1},{"playerMove":2,"result":-1},{"playerMove":0,"result":-1},{"playerMove":2,"result":-1},{"playerMove":2,"result":1},{"playerMove":1,"result":0},{"playerMove":0,"result":0},{"playerMove":2,"result":-1},{"playerMove":1,"result":-1},{"playerMove":0,"result":-1},{"playerMove":2,"result":1},{"playerMove":0,"result":-1},{"playerMove":2,"result":-1},{"playerMove":1,"result":-1},{"playerMove":2,"result":1},{"playerMove":0,"result":-1},{"playerMove":1,"result":1},{"playerMove":2,"result":1},{"playerMove":0,"result":0},{"playerMove":1,"result":-1},{"playerMove":2,"result":-1},{"playerMove":0,"result":1},{"playerMove":2,"result":0},{"playerMove":1,"result":-1},{"playerMove":2,"result":1},{"playerMove":1,"result":1},{"playerMove":0,"result":-1},{"playerMove":2,"result":-1},{"playerMove":1,"result":-1},{"playerMove":0,"result":-1},{"playerMove":1,"result":1},{"playerMove":0,"result":0},{"playerMove":2,"result":-1},{"playerMove":1,"result":-1},{"playerMove":0,"result":-1},{"playerMove":2,"result":0},{"playerMove":1,"result":-1},{"playerMove":0,"result":-1},{"playerMove":2,"result":-1},{"playerMove":1,"result":-1},{"playerMove":0,"result":-1},{"playerMove":2,"result":1},{"playerMove":0,"result":0},{"playerMove":1,"result":1},{"playerMove":2,"result":-1},{"playerMove":1,"result":-1},{"playerMove":0,"result":-1},{"playerMove":2,"result":-1},{"playerMove":1,"result":1},{"playerMove":0,"result":-1},{"playerMove":2,"result":-1},{"playerMove":1,"result":1},{"playerMove":2,"result":1},{"playerMove":0,"result":1},{"playerMove":1,"result":1},{"playerMove":2,"result":-1},{"playerMove":0,"result":1},{"playerMove":2,"result":-1},{"playerMove":1,"result":-1},{"playerMove":2,"result":1},{"playerMove":0,"result":-1},{"playerMove":1,"result":-1},{"playerMove":0,"result":-1},{"playerMove":2,"result":-1},{"playerMove":1,"result":-1},{"playerMove":0,"result":0},{"playerMove":2,"result":-1},{"playerMove":1,"result":-1},{"playerMove":2,"result":1},{"playerMove":0,"result":-1},{"playerMove":2,"result":0},{"playerMove":1,"result":-1},{"playerMove":0,"result":-1},{"playerMove":2,"result":-1},{"playerMove":1,"result":-1},{"playerMove":0,"result":-1},{"playerMove":2,"result":-1},{"playerMove":1,"result":0},{"playerMove":2,"result":-1},{"playerMove":0,"result":1},{"playerMove":1,"result":1},{"playerMove":2,"result":0},{"playerMove":0,"result":1},{"playerMove":2,"result":0},{"playerMove":0,"result":1},{"playerMove":2,"result":-1},{"playerMove":2,"result":0},{"playerMove":1,"result":-1},{"playerMove":0,"result":-1},{"playerMove":2,"result":1},{"playerMove":1,"result":0},{"playerMove":2,"result":-1},{"playerMove":0,"result":0},{"playerMove":1,"result":1},{"playerMove":2,"result":1},{"playerMove":1,"result":0},{"playerMove":0,"result":1},{"playerMove":2,"result":1},{"playerMove":1,"result":-1},{"playerMove":0,"result":0},{"playerMove":2,"result":0},{"playerMove":0,"result":1},{"playerMove":2,"result":0},{"playerMove":1,"result":1},{"playerMove":0,"result":-1},{"playerMove":2,"result":-1},{"playerMove":1,"result":1},{"playerMove":0,"result":0},{"playerMove":1,"result":1},{"playerMove":2,"result":1},{"playerMove":0,"result":1},{"playerMove":1,"result":-1},{"playerMove":0,"result":-1},{"playerMove":2,"result":-1},{"playerMove":1,"result":-1},{"playerMove":0,"result":-1},{"playerMove":2,"result":-1},{"playerMove":1,"result":-1},{"playerMove":0,"result":0},{"playerMove":2,"result":0},{"playerMove":1,"result":-1},{"playerMove":0,"result":-1},{"playerMove":2,"result":-1},{"playerMove":1,"result":-1},{"playerMove":0,"result":-1},{"playerMove":2,"result":-1},{"playerMove":1,"result":-1},{"playerMove":0,"result":-1},{"playerMove":2,"result":-1},{"playerMove":1,"result":0},{"playerMove":0,"result":0},{"playerMove":2,"result":-1},{"playerMove":1,"result":0},{"playerMove":0,"result":-1},{"playerMove":2,"result":-1},{"playerMove":1,"result":-1},{"playerMove":0,"result":-1},{"playerMove":2,"result":-1},{"playerMove":1,"result":-1},{"playerMove":0,"result":1},{"playerMove":2,"result":-1},{"playerMove":1,"result":-1},{"playerMove":0,"result":0},{"playerMove":2,"result":-1},{"playerMove":1,"result":-1},{"playerMove":0,"result":-1},{"playerMove":2,"result":1},{"playerMove":1,"result":1},{"playerMove":0,"result":1},{"playerMove":2,"result":-1},{"playerMove":1,"result":-1},{"playerMove":0,"result":0},{"playerMove":2,"result":-1},{"playerMove":1,"result":-1},{"playerMove":0,"result":-1},{"playerMove":2,"result":-1},{"playerMove":1,"result":-1},{"playerMove":0,"result":-1},{"playerMove":2,"result":-1},{"playerMove":1,"result":0},{"playerMove":0,"result":-1},{"playerMove":2,"result":-1},{"playerMove":1,"result":-1},{"playerMove":0,"result":0},{"playerMove":2,"result":0},{"playerMove":1,"result":0},{"playerMove":0,"result":0},{"playerMove":2,"result":-1},{"playerMove":1,"result":-1},{"playerMove":0,"result":1},{"playerMove":2,"result":-1},{"playerMove":1,"result":-1},{"playerMove":0,"result":-1},{"playerMove":2,"result":-1},{"playerMove":1,"result":-1},{"playerMove":0,"result":-1},{"playerMove":2,"result":-1},{"playerMove":1,"result":1},{"playerMove":0,"result":-1},{"playerMove":2,"result":-1},{"playerMove":1,"result":-1},{"playerMove":0,"result":-1},{"playerMove":2,"result":-1},{"playerMove":1,"result":0},{"playerMove":0,"result":-1},{"playerMove":2,"result":0},{"playerMove":1,"result":-1},{"playerMove":0,"result":-1},{"playerMove":2,"result":-1},{"playerMove":1,"result":-1},{"playerMove":0,"result":-1},{"playerMove":2,"result":-1},{"playerMove":1,"result":0},{"playerMove":0,"result":-1},{"playerMove":2,"result":-1},{"playerMove":1,"result":-1},{"playerMove":0,"result":-1},{"playerMove":2,"result":-1},{"playerMove":1,"result":-1},{"playerMove":0,"result":-1},{"playerMove":2,"result":-1},{"playerMove":1,"result":-1},{"playerMove":0,"result":-1},{"playerMove":2,"result":-1},{"playerMove":1,"result":-1},{"playerMove":0,"result":1},{"playerMove":2,"result":0},{"playerMove":0,"result":0},{"playerMove":1,"result":-1},{"playerMove":2,"result":1},{"playerMove":0,"result":1},{"playerMove":1,"result":1},{"playerMove":2,"result":-1},{"playerMove":0,"result":1},{"playerMove":1,"result":1},{"playerMove":2,"result":1},{"playerMove":0,"result":-1},{"playerMove":1,"result":-1},{"playerMove":2,"result":1},{"playerMove":0,"result":1},{"playerMove":1,"result":1},{"playerMove":2,"result":1},{"playerMove":0,"result":-1},{"playerMove":1,"result":1},{"playerMove":0,"result":-1},{"playerMove":1,"result":1},{"playerMove":2,"result":1},{"playerMove":0,"result":-1},{"playerMove":1,"result":1},{"playerMove":0,"result":-1},{"playerMove":2,"result":-1},{"playerMove":1,"result":-1},{"playerMove":0,"result":-1},{"playerMove":1,"result":1},{"playerMove":2,"result":1},{"playerMove":0,"result":-1},{"playerMove":1,"result":-1},{"playerMove":0,"result":0},{"playerMove":2,"result":-1},{"playerMove":1,"result":-1},{"playerMove":0,"result":-1},{"playerMove":1,"result":1},{"playerMove":2,"result":-1},{"playerMove":0,"result":1},{"playerMove":1,"result":1},{"playerMove":0,"result":0},{"playerMove":2,"result":-1},{"playerMove":1,"result":-1},{"playerMove":0,"result":-1},{"playerMove":1,"result":1},{"playerMove":2,"result":1},{"playerMove":0,"result":-1},{"playerMove":1,"result":1},{"playerMove":0,"result":0},{"playerMove":2,"result":-1},{"playerMove":1,"result":-1},{"playerMove":0,"result":-1},{"playerMove":1,"result":-1},{"playerMove":2,"result":1},{"playerMove":0,"result":-1},{"playerMove":1,"result":1},{"playerMove":0,"result":-1},{"playerMove":2,"result":-1},{"playerMove":1,"result":-1},{"playerMove":0,"result":-1},{"playerMove":2,"result":-1},{"playerMove":1,"result":-1},{"playerMove":0,"result":-1},{"playerMove":1,"result":1},{"playerMove":2,"result":-1},{"playerMove":0,"result":1},{"playerMove":1,"result":-1},{"playerMove":0,"result":-1},{"playerMove":2,"result":-1},{"playerMove":1,"result":-1},{"playerMove":0,"result":-1},{"playerMove":1,"result":1},{"playerMove":2,"result":1},{"playerMove":0,"result":-1},{"playerMove":1,"result":-1},{"playerMove":2,"result":1},{"playerMove":0,"result":1},{"playerMove":1,"result":1},{"playerMove":2,"result":-1},{"playerMove":0,"result":1},{"playerMove":1,"result":-1},{"playerMove":2,"result":1},{"playerMove":0,"result":-1},{"playerMove":1,"result":-1},{"playerMove":0,"result":0},{"playerMove":2,"result":-1},{"playerMove":1,"result":-1},{"playerMove":0,"result":-1},{"playerMove":1,"result":-1},{"playerMove":2,"result":1},{"playerMove":0,"result":1},{"playerMove":1,"result":-1},{"playerMove":2,"result":1},{"playerMove":0,"result":-1},{"playerMove":1,"result":1},{"playerMove":2,"result":-1},{"playerMove":0,"result":1},{"playerMove":1,"result":1},{"playerMove":2,"result":-1},{"playerMove":0,"result":-1},{"playerMove":1,"result":1},{"playerMove":2,"result":1},{"playerMove":0,"result":-1},{"playerMove":1,"result":1},{"playerMove":2,"result":-1},{"playerMove":0,"result":1},{"playerMove":1,"result":1},{"playerMove":2,"result":-1},{"playerMove":0,"result":1},{"playerMove":2,"result":0},{"playerMove":2,"result":0},{"playerMove":0,"result":1},{"playerMove":1,"result":-1},{"playerMove":2,"result":-1},{"playerMove":0,"result":-1},{"playerMove":1,"result":1},{"playerMove":0,"result":0},{"playerMove":1,"result":-1},{"playerMove":2,"result":1},{"playerMove":0,"result":-1},{"playerMove":1,"result":1},{"playerMove":2,"result":-1},{"playerMove":0,"result":1},{"playerMove":1,"result":1},{"playerMove":2,"result":1},{"playerMove":0,"result":-1},{"playerMove":2,"result":1},{"playerMove":0,"result":0},{"playerMove":0,"result":1},{"playerMove":2,"result":0},{"playerMove":1,"result":-1},{"playerMove":2,"result":1},{"playerMove":0,"result":-1},{"playerMove":2,"result":-1},{"playerMove":1,"result":-1},{"playerMove":2,"result":-1},{"playerMove":0,"result":1},{"playerMove":1,"result":-1},{"playerMove":2,"result":-1},{"playerMove":0,"result":1},{"playerMove":1,"result":1},{"playerMove":2,"result":-1},{"playerMove":0,"result":1},{"playerMove":2,"result":-1},{"playerMove":1,"result":-1},{"playerMove":2,"result":1},{"playerMove":0,"result":-1}],"stats":{"nOfLoses":280,"nOfRounds":500,"nOfTies":75,"nOfWins":75,"playerWinRate":0.29,"iaWinRate":0.56,"tieRate":0.15}},{"rounds":[{"playerMove":0,"result":-1},{"playerMove":1,"result":0},{"playerMove":1,"result":-1},{"playerMove":2,"result":0},{"playerMove":2,"result":0},{"playerMove":1,"result":1},{"playerMove":2,"result":1},{"playerMove":2,"result":1},{"playerMove":1,"result":-1},{"playerMove":0,"result":1},{"playerMove":1,"result":1},{"playerMove":0,"result":0},{"playerMove":1,"result":-1},{"playerMove":1,"result":0},{"playerMove":2,"result":0},{"playerMove":0,"result":0},{"playerMove":2,"result":1},{"playerMove":1,"result":0},{"playerMove":2,"result":-1},{"playerMove":1,"result":-1},{"playerMove":0,"result":0},{"playerMove":0,"result":1},{"playerMove":2,"result":1},{"playerMove":2,"result":-1},{"playerMove":2,"result":1},{"playerMove":1,"result":1},{"playerMove":0,"result":1},{"playerMove":0,"result":-1},{"playerMove":0,"result":1},{"playerMove":1,"result":-1},{"playerMove":2,"result":1},{"playerMove":2,"result":-1},{"playerMove":1,"result":1},{"playerMove":0,"result":0},{"playerMove":0,"result":0},{"playerMove":0,"result":-1},{"playerMove":1,"result":1},{"playerMove":1,"result":0},{"playerMove":2,"result":-1},{"playerMove":2,"result":1},{"playerMove":1,"result":-1},{"playerMove":0,"result":1},{"playerMove":2,"result":0},{"playerMove":1,"result":-1},{"playerMove":0,"result":1},{"playerMove":0,"result":-1},{"playerMove":1,"result":1},{"playerMove":0,"result":1},{"playerMove":2,"result":-1},{"playerMove":1,"result":1},{"playerMove":0,"result":-1},{"playerMove":2,"result":-1},{"playerMove":1,"result":-1},{"playerMove":0,"result":-1},{"playerMove":2,"result":0},{"playerMove":1,"result":0},{"playerMove":0,"result":-1},{"playerMove":2,"result":-1},{"playerMove":1,"result":0},{"playerMove":0,"result":0},{"playerMove":2,"result":1},{"playerMove":1,"result":1},{"playerMove":0,"result":-1},{"playerMove":2,"result":-1},{"playerMove":1,"result":-1},{"playerMove":0,"result":-1},{"playerMove":2,"result":0},{"playerMove":1,"result":0},{"playerMove":0,"result":-1},{"playerMove":2,"result":1},{"playerMove":1,"result":-1},{"playerMove":0,"result":0},{"playerMove":2,"result":1},{"playerMove":1,"result":-1},{"playerMove":0,"result":-1},{"playerMove":2,"result":0},{"playerMove":1,"result":-1},{"playerMove":0,"result":-1},{"playerMove":2,"result":0},{"playerMove":1,"result":1},{"playerMove":0,"result":-1},{"playerMove":1,"result":1},{"playerMove":0,"result":1},{"playerMove":1,"result":-1},{"playerMove":0,"result":-1},{"playerMove":2,"result":0},{"playerMove":1,"result":-1},{"playerMove":0,"result":-1},{"playerMove":2,"result":0},{"playerMove":1,"result":-1},{"playerMove":0,"result":-1},{"playerMove":2,"result":-1},{"playerMove":1,"result":-1},{"playerMove":0,"result":-1},{"playerMove":2,"result":-1},{"playerMove":1,"result":1},{"playerMove":0,"result":0},{"playerMove":2,"result":0},{"playerMove":1,"result":-1},{"playerMove":0,"result":-1},{"playerMove":1,"result":0},{"playerMove":0,"result":-1},{"playerMove":1,"result":-1},{"playerMove":0,"result":0},{"playerMove":1,"result":-1},{"playerMove":0,"result":-1},{"playerMove":1,"result":1},{"playerMove":0,"result":-1},{"playerMove":1,"result":1},{"playerMove":0,"result":-1},{"playerMove":1,"result":1},{"playerMove":0,"result":-1},{"playerMove":1,"result":1},{"playerMove":0,"result":1},{"playerMove":1,"result":-1},{"playerMove":0,"result":-1},{"playerMove":1,"result":1},{"playerMove":0,"result":-1},{"playerMove":1,"result":1},{"playerMove":0,"result":1},{"playerMove":1,"result":1},{"playerMove":0,"result":1},{"playerMove":2,"result":0},{"playerMove":1,"result":-1},{"playerMove":0,"result":-1},{"playerMove":2,"result":0},{"playerMove":1,"result":-1},{"playerMove":0,"result":-1},{"playerMove":2,"result":1},{"playerMove":1,"result":-1},{"playerMove":0,"result":-1},{"playerMove":2,"result":0},{"playerMove":1,"result":-1},{"playerMove":0,"result":-1},{"playerMove":2,"result":-1},{"playerMove":1,"result":-1},{"playerMove":0,"result":-1},{"playerMove":2,"result":0},{"playerMove":1,"result":-1},{"playerMove":0,"result":-1},{"playerMove":2,"result":-1},{"playerMove":1,"result":-1},{"playerMove":0,"result":-1},{"playerMove":2,"result":-1},{"playerMove":1,"result":1},{"playerMove":1,"result":-1},{"playerMove":1,"result":0},{"playerMove":0,"result":1},{"playerMove":1,"result":-1},{"playerMove":0,"result":-1},{"playerMove":1,"result":0},{"playerMove":0,"result":-1},{"playerMove":1,"result":1},{"playerMove":0,"result":-1},{"playerMove":1,"result":1},{"playerMove":0,"result":-1},{"playerMove":1,"result":1},{"playerMove":0,"result":-1},{"playerMove":2,"result":-1},{"playerMove":1,"result":-1},{"playerMove":0,"result":-1},{"playerMove":2,"result":0},{"playerMove":1,"result":-1},{"playerMove":2,"result":1},{"playerMove":2,"result":0},{"playerMove":1,"result":-1},{"playerMove":0,"result":-1},{"playerMove":1,"result":1},{"playerMove":0,"result":-1},{"playerMove":1,"result":1},{"playerMove":0,"result":-1},{"playerMove":0,"result":1},{"playerMove":1,"result":-1},{"playerMove":0,"result":-1},{"playerMove":1,"result":1},{"playerMove":0,"result":-1},{"playerMove":1,"result":-1},{"playerMove":0,"result":-1},{"playerMove":1,"result":-1},{"playerMove":0,"result":-1},{"playerMove":1,"result":-1},{"playerMove":0,"result":-1},{"playerMove":2,"result":0},{"playerMove":1,"result":-1},{"playerMove":0,"result":-1},{"playerMove":2,"result":-1},{"playerMove":1,"result":-1},{"playerMove":0,"result":0},{"playerMove":1,"result":1},{"playerMove":0,"result":-1},{"playerMove":1,"result":-1},{"playerMove":1,"result":0},{"playerMove":1,"result":-1},{"playerMove":0,"result":-1},{"playerMove":1,"result":1},{"playerMove":0,"result":-1},{"playerMove":2,"result":0},{"playerMove":1,"result":-1},{"playerMove":0,"result":0},{"playerMove":2,"result":-1},{"playerMove":1,"result":-1},{"playerMove":0,"result":-1},{"playerMove":2,"result":0},{"playerMove":1,"result":-1},{"playerMove":0,"result":-1},{"playerMove":2,"result":-1},{"playerMove":1,"result":-1},{"playerMove":0,"result":-1},{"playerMove":2,"result":-1},{"playerMove":1,"result":-1},{"playerMove":0,"result":-1},{"playerMove":2,"result":-1},{"playerMove":1,"result":1},{"playerMove":0,"result":-1},{"playerMove":2,"result":-1},{"playerMove":1,"result":-1},{"playerMove":0,"result":-1},{"playerMove":2,"result":-1},{"playerMove":1,"result":-1},{"playerMove":0,"result":-1},{"playerMove":2,"result":-1},{"playerMove":1,"result":1},{"playerMove":0,"result":-1},{"playerMove":2,"result":1},{"playerMove":1,"result":-1},{"playerMove":0,"result":-1},{"playerMove":1,"result":1},{"playerMove":2,"result":1},{"playerMove":0,"result":1},{"playerMove":2,"result":0},{"playerMove":1,"result":-1},{"playerMove":0,"result":-1},{"playerMove":2,"result":-1},{"playerMove":1,"result":-1},{"playerMove":0,"result":-1},{"playerMove":2,"result":1},{"playerMove":1,"result":-1},{"playerMove":0,"result":-1},{"playerMove":2,"result":0},{"playerMove":1,"result":-1},{"playerMove":0,"result":-1},{"playerMove":2,"result":0},{"playerMove":1,"result":-1},{"playerMove":0,"result":-1},{"playerMove":2,"result":-1},{"playerMove":1,"result":-1},{"playerMove":0,"result":-1},{"playerMove":1,"result":1},{"playerMove":1,"result":0},{"playerMove":0,"result":0},{"playerMove":1,"result":1},{"playerMove":0,"result":-1},{"playerMove":1,"result":0},{"playerMove":0,"result":-1},{"playerMove":1,"result":-1},{"playerMove":0,"result":-1},{"playerMove":1,"result":-1},{"playerMove":0,"result":-1},{"playerMove":1,"result":1},{"playerMove":0,"result":-1},{"playerMove":1,"result":-1},{"playerMove":0,"result":-1},{"playerMove":1,"result":1},{"playerMove":0,"result":-1},{"playerMove":2,"result":-1},{"playerMove":1,"result":-1},{"playerMove":0,"result":-1},{"playerMove":1,"result":1},{"playerMove":0,"result":-1},{"playerMove":1,"result":-1},{"playerMove":0,"result":-1},{"playerMove":1,"result":-1},{"playerMove":0,"result":-1},{"playerMove":2,"result":-1},{"playerMove":1,"result":-1},{"playerMove":0,"result":-1},{"playerMove":1,"result":1},{"playerMove":2,"result":1},{"playerMove":0,"result":0},{"playerMove":2,"result":0},{"playerMove":1,"result":-1},{"playerMove":0,"result":0},{"playerMove":1,"result":1},{"playerMove":0,"result":-1},{"playerMove":1,"result":1},{"playerMove":0,"result":-1},{"playerMove":1,"result":-1},{"playerMove":0,"result":-1},{"playerMove":1,"result":-1},{"playerMove":2,"result":1},{"playerMove":2,"result":-1},{"playerMove":1,"result":-1},{"playerMove":0,"result":-1},{"playerMove":0,"result":0},{"playerMove":0,"result":1},{"playerMove":0,"result":0},{"playerMove":0,"result":1},{"playerMove":0,"result":-1},{"playerMove":0,"result":1},{"playerMove":0,"result":-1},{"playerMove":0,"result":1},{"playerMove":0,"result":1},{"playerMove":0,"result":0},{"playerMove":0,"result":0},{"playerMove":0,"result":-1},{"playerMove":0,"result":0},{"playerMove":0,"result":0},{"playerMove":0,"result":1},{"playerMove":0,"result":1},{"playerMove":0,"result":1},{"playerMove":0,"result":-1},{"playerMove":0,"result":1},{"playerMove":0,"result":-1},{"playerMove":0,"result":1},{"playerMove":0,"result":1},{"playerMove":0,"result":-1},{"playerMove":0,"result":0},{"playerMove":0,"result":0},{"playerMove":0,"result":1},{"playerMove":0,"result":0},{"playerMove":0,"result":1},{"playerMove":0,"result":-1},{"playerMove":0,"result":-1},{"playerMove":0,"result":0},{"playerMove":0,"result":0},{"playerMove":0,"result":1},{"playerMove":0,"result":-1},{"playerMove":0,"result":1},{"playerMove":0,"result":0},{"playerMove":0,"result":-1},{"playerMove":0,"result":1},{"playerMove":0,"result":1},{"playerMove":0,"result":-1},{"playerMove":0,"result":-1},{"playerMove":0,"result":1},{"playerMove":0,"result":1},{"playerMove":0,"result":-1},{"playerMove":0,"result":-1},{"playerMove":0,"result":1},{"playerMove":0,"result":1},{"playerMove":0,"result":0},{"playerMove":0,"result":1},{"playerMove":0,"result":1},{"playerMove":0,"result":-1},{"playerMove":0,"result":1},{"playerMove":0,"result":-1},{"playerMove":0,"result":1},{"playerMove":0,"result":-1},{"playerMove":0,"result":1},{"playerMove":0,"result":0},{"playerMove":0,"result":1},{"playerMove":0,"result":-1},{"playerMove":0,"result":1},{"playerMove":0,"result":-1},{"playerMove":0,"result":0},{"playerMove":0,"result":0},{"playerMove":0,"result":0},{"playerMove":0,"result":1},{"playerMove":1,"result":1},{"playerMove":1,"result":0},{"playerMove":1,"result":1},{"playerMove":1,"result":0},{"playerMove":1,"result":0},{"playerMove":1,"result":-1},{"playerMove":1,"result":0},{"playerMove":2,"result":1},{"playerMove":2,"result":-1},{"playerMove":2,"result":-1},{"playerMove":2,"result":0},{"playerMove":2,"result":0},{"playerMove":2,"result":0},{"playerMove":0,"result":1},{"playerMove":0,"result":-1},{"playerMove":0,"result":0},{"playerMove":0,"result":-1},{"playerMove":0,"result":0},{"playerMove":1,"result":1},{"playerMove":1,"result":0},{"playerMove":1,"result":1},{"playerMove":1,"result":-1},{"playerMove":1,"result":0},{"playerMove":1,"result":0},{"playerMove":1,"result":0},{"playerMove":1,"result":-1},{"playerMove":1,"result":0},{"playerMove":1,"result":1},{"playerMove":1,"result":0},{"playerMove":1,"result":0},{"playerMove":0,"result":1},{"playerMove":0,"result":-1},{"playerMove":2,"result":1},{"playerMove":1,"result":1},{"playerMove":0,"result":-1},{"playerMove":2,"result":-1},{"playerMove":1,"result":-1},{"playerMove":0,"result":-1},{"playerMove":1,"result":-1},{"playerMove":0,"result":-1},{"playerMove":0,"result":-1},{"playerMove":0,"result":0},{"playerMove":0,"result":-1},{"playerMove":0,"result":0},{"playerMove":0,"result":-1},{"playerMove":0,"result":1},{"playerMove":0,"result":-1},{"playerMove":0,"result":-1},{"playerMove":0,"result":-1},{"playerMove":0,"result":1},{"playerMove":0,"result":-1},{"playerMove":0,"result":1},{"playerMove":1,"result":0},{"playerMove":2,"result":0},{"playerMove":2,"result":0},{"playerMove":2,"result":0},{"playerMove":2,"result":0},{"playerMove":2,"result":0},{"playerMove":2,"result":-1},{"playerMove":2,"result":0},{"playerMove":2,"result":0},{"playerMove":1,"result":0},{"playerMove":0,"result":-1},{"playerMove":1,"result":-1},{"playerMove":0,"result":-1},{"playerMove":1,"result":-1},{"playerMove":1,"result":0},{"playerMove":1,"result":1},{"playerMove":1,"result":0},{"playerMove":1,"result":-1},{"playerMove":1,"result":-1},{"playerMove":1,"result":0},{"playerMove":1,"result":1},{"playerMove":0,"result":-1},{"playerMove":0,"result":0},{"playerMove":0,"result":-1},{"playerMove":0,"result":-1},{"playerMove":0,"result":-1},{"playerMove":0,"result":1},{"playerMove":0,"result":-1},{"playerMove":0,"result":-1},{"playerMove":0,"result":-1},{"playerMove":0,"result":1},{"playerMove":0,"result":-1},{"playerMove":0,"result":0},{"playerMove":0,"result":-1},{"playerMove":0,"result":1},{"playerMove":0,"result":-1},{"playerMove":0,"result":1},{"playerMove":0,"result":-1},{"playerMove":0,"result":1},{"playerMove":0,"result":-1},{"playerMove":2,"result":0},{"playerMove":2,"result":0},{"playerMove":2,"result":0},{"playerMove":1,"result":-1},{"playerMove":0,"result":-1},{"playerMove":2,"result":1},{"playerMove":1,"result":1},{"playerMove":0,"result":-1},{"playerMove":2,"result":1},{"playerMove":1,"result":-1},{"playerMove":0,"result":-1},{"playerMove":2,"result":1},{"playerMove":2,"result":0},{"playerMove":2,"result":0},{"playerMove":2,"result":0},{"playerMove":2,"result":-1},{"playerMove":1,"result":-1},{"playerMove":1,"result":0},{"playerMove":0,"result":0},{"playerMove":1,"result":0},{"playerMove":0,"result":-1},{"playerMove":1,"result":1},{"playerMove":0,"result":-1},{"playerMove":1,"result":0},{"playerMove":2,"result":0},{"playerMove":1,"result":-1},{"playerMove":0,"result":0},{"playerMove":1,"result":0},{"playerMove":0,"result":-1},{"playerMove":1,"result":1},{"playerMove":0,"result":-1},{"playerMove":1,"result":1},{"playerMove":0,"result":1},{"playerMove":1,"result":0},{"playerMove":0,"result":-1},{"playerMove":1,"result":-1},{"playerMove":1,"result":1},{"playerMove":1,"result":-1},{"playerMove":0,"result":-1},{"playerMove":1,"result":1},{"playerMove":0,"result":-1},{"playerMove":1,"result":0},{"playerMove":0,"result":1},{"playerMove":1,"result":0},{"playerMove":1,"result":0},{"playerMove":0,"result":1},{"playerMove":1,"result":0},{"playerMove":0,"result":-1},{"playerMove":1,"result":1},{"playerMove":0,"result":-1}],"stats":{"nOfLoses":251,"nOfRounds":500,"nOfTies":118,"nOfWins":118,"playerWinRate":0.262,"iaWinRate":0.502,"tieRate":0.236}},{"rounds":[{"playerMove":0,"result":1},{"playerMove":1,"result":0},{"playerMove":0,"result":0},{"playerMove":2,"result":0},{"playerMove":1,"result":0},{"playerMove":0,"result":-1},{"playerMove":2,"result":0},{"playerMove":1,"result":0},{"playerMove":0,"result":1},{"playerMove":0,"result":1},{"playerMove":0,"result":0},{"playerMove":0,"result":0},{"playerMove":0,"result":-1},{"playerMove":0,"result":-1},{"playerMove":1,"result":0},{"playerMove":2,"result":1},{"playerMove":2,"result":0},{"playerMove":1,"result":-1},{"playerMove":0,"result":1},{"playerMove":2,"result":-1},{"playerMove":1,"result":1},{"playerMove":1,"result":1},{"playerMove":1,"result":0},{"playerMove":1,"result":-1},{"playerMove":1,"result":1},{"playerMove":1,"result":-1},{"playerMove":1,"result":-1},{"playerMove":1,"result":-1},{"playerMove":1,"result":-1},{"playerMove":1,"result":-1},{"playerMove":1,"result":-1},{"playerMove":1,"result":-1},{"playerMove":1,"result":-1},{"playerMove":1,"result":-1},{"playerMove":1,"result":-1},{"playerMove":1,"result":-1},{"playerMove":1,"result":-1},{"playerMove":1,"result":-1},{"playerMove":1,"result":-1},{"playerMove":1,"result":-1},{"playerMove":1,"result":-1},{"playerMove":1,"result":-1},{"playerMove":1,"result":-1},{"playerMove":1,"result":-1},{"playerMove":1,"result":-1},{"playerMove":1,"result":-1},{"playerMove":1,"result":-1},{"playerMove":1,"result":-1},{"playerMove":1,"result":-1},{"playerMove":1,"result":-1},{"playerMove":1,"result":-1},{"playerMove":1,"result":-1},{"playerMove":1,"result":-1},{"playerMove":1,"result":-1},{"playerMove":1,"result":-1},{"playerMove":1,"result":-1},{"playerMove":1,"result":-1},{"playerMove":2,"result":0},{"playerMove":2,"result":1},{"playerMove":2,"result":1},{"playerMove":2,"result":1},{"playerMove":2,"result":0},{"playerMove":2,"result":0},{"playerMove":2,"result":-1},{"playerMove":2,"result":-1},{"playerMove":2,"result":-1},{"playerMove":2,"result":-1},{"playerMove":2,"result":-1},{"playerMove":2,"result":-1},{"playerMove":2,"result":-1},{"playerMove":2,"result":-1},{"playerMove":2,"result":-1},{"playerMove":2,"result":-1},{"playerMove":2,"result":-1},{"playerMove":2,"result":-1},{"playerMove":2,"result":-1},{"playerMove":2,"result":-1},{"playerMove":2,"result":-1},{"playerMove":2,"result":-1},{"playerMove":2,"result":-1},{"playerMove":0,"result":0},{"playerMove":0,"result":-1},{"playerMove":0,"result":1},{"playerMove":0,"result":-1},{"playerMove":0,"result":0},{"playerMove":0,"result":1},{"playerMove":0,"result":1},{"playerMove":0,"result":-1},{"playerMove":0,"result":-1},{"playerMove":0,"result":-1},{"playerMove":0,"result":-1},{"playerMove":0,"result":-1},{"playerMove":0,"result":-1},{"playerMove":0,"result":-1},{"playerMove":0,"result":-1},{"playerMove":0,"result":-1},{"playerMove":0,"result":-1},{"playerMove":0,"result":-1},{"playerMove":1,"result":0},{"playerMove":0,"result":-1},{"playerMove":2,"result":1},{"playerMove":1,"result":1},{"playerMove":0,"result":-1},{"playerMove":2,"result":-1},{"playerMove":1,"result":1},{"playerMove":0,"result":0},{"playerMove":1,"result":1},{"playerMove":0,"result":1},{"playerMove":1,"result":1},{"playerMove":0,"result":1},{"playerMove":1,"result":-1},{"playerMove":0,"result":-1},{"playerMove":1,"result":-1},{"playerMove":0,"result":-1},{"playerMove":1,"result":-1},{"playerMove":0,"result":-1},{"playerMove":1,"result":-1},{"playerMove":0,"result":-1},{"playerMove":2,"result":0},{"playerMove":1,"result":0},{"playerMove":0,"result":-1},{"playerMove":1,"result":-1},{"playerMove":0,"result":1},{"playerMove":1,"result":1},{"playerMove":2,"result":0},{"playerMove":2,"result":0},{"playerMove":2,"result":-1},{"playerMove":1,"result":1},{"playerMove":0,"result":-1},{"playerMove":2,"result":-1},{"playerMove":2,"result":1},{"playerMove":1,"result":-1},{"playerMove":0,"result":1},{"playerMove":1,"result":1},{"playerMove":0,"result":0},{"playerMove":1,"result":-1},{"playerMove":1,"result":0},{"playerMove":1,"result":-1},{"playerMove":0,"result":-1},{"playerMove":1,"result":-1},{"playerMove":0,"result":-1},{"playerMove":1,"result":-1},{"playerMove":0,"result":1},{"playerMove":1,"result":-1},{"playerMove":0,"result":-1},{"playerMove":0,"result":1},{"playerMove":2,"result":0},{"playerMove":1,"result":0},{"playerMove":0,"result":-1},{"playerMove":0,"result":1},{"playerMove":1,"result":0},{"playerMove":0,"result":-1},{"playerMove":0,"result":-1},{"playerMove":1,"result":-1},{"playerMove":0,"result":-1},{"playerMove":0,"result":1},{"playerMove":1,"result":-1},{"playerMove":0,"result":-1},{"playerMove":0,"result":-1},{"playerMove":1,"result":-1},{"playerMove":2,"result":1},{"playerMove":2,"result":-1},{"playerMove":2,"result":0},{"playerMove":2,"result":-1},{"playerMove":2,"result":-1},{"playerMove":2,"result":-1},{"playerMove":2,"result":-1},{"playerMove":2,"result":-1},{"playerMove":2,"result":-1},{"playerMove":2,"result":-1},{"playerMove":0,"result":0},{"playerMove":0,"result":0},{"playerMove":0,"result":1},{"playerMove":1,"result":1},{"playerMove":1,"result":0},{"playerMove":1,"result":1},{"playerMove":0,"result":-1},{"playerMove":1,"result":0},{"playerMove":0,"result":-1},{"playerMove":1,"result":0},{"playerMove":1,"result":0},{"playerMove":1,"result":0},{"playerMove":1,"result":0},{"playerMove":0,"result":1},{"playerMove":1,"result":-1},{"playerMove":0,"result":-1},{"playerMove":1,"result":1},{"playerMove":0,"result":1},{"playerMove":1,"result":-1},{"playerMove":0,"result":-1},{"playerMove":1,"result":-1},{"playerMove":0,"result":-1},{"playerMove":1,"result":-1},{"playerMove":0,"result":-1},{"playerMove":1,"result":-1},{"playerMove":0,"result":-1},{"playerMove":1,"result":-1},{"playerMove":0,"result":-1},{"playerMove":1,"result":-1},{"playerMove":1,"result":0},{"playerMove":2,"result":0},{"playerMove":1,"result":1},{"playerMove":0,"result":-1},{"playerMove":1,"result":-1},{"playerMove":0,"result":0},{"playerMove":0,"result":0},{"playerMove":0,"result":-1},{"playerMove":1,"result":0},{"playerMove":0,"result":1},{"playerMove":1,"result":-1},{"playerMove":0,"result":-1},{"playerMove":1,"result":0},{"playerMove":0,"result":-1},{"playerMove":1,"result":-1},{"playerMove":0,"result":-1},{"playerMove":1,"result":-1},{"playerMove":0,"result":-1},{"playerMove":1,"result":-1},{"playerMove":0,"result":-1},{"playerMove":2,"result":0},{"playerMove":1,"result":0},{"playerMove":0,"result":1},{"playerMove":1,"result":1},{"playerMove":1,"result":0},{"playerMove":0,"result":-1},{"playerMove":1,"result":-1},{"playerMove":0,"result":1},{"playerMove":1,"result":1},{"playerMove":0,"result":1},{"playerMove":1,"result":-1},{"playerMove":1,"result":-1},{"playerMove":0,"result":-1},{"playerMove":1,"result":-1},{"playerMove":0,"result":-1},{"playerMove":1,"result":-1},{"playerMove":0,"result":0},{"playerMove":1,"result":-1},{"playerMove":0,"result":1},{"playerMove":1,"result":-1},{"playerMove":0,"result":-1},{"playerMove":1,"result":-1},{"playerMove":0,"result":-1},{"playerMove":1,"result":-1},{"playerMove":0,"result":-1},{"playerMove":1,"result":-1},{"playerMove":0,"result":-1},{"playerMove":1,"result":-1},{"playerMove":0,"result":-1},{"playerMove":1,"result":-1},{"playerMove":0,"result":-1},{"playerMove":0,"result":1},{"playerMove":0,"result":-1},{"playerMove":0,"result":-1},{"playerMove":0,"result":-1},{"playerMove":0,"result":-1},{"playerMove":0,"result":-1},{"playerMove":0,"result":-1},{"playerMove":0,"result":-1},{"playerMove":0,"result":-1},{"playerMove":0,"result":-1},{"playerMove":0,"result":-1},{"playerMove":0,"result":-1},{"playerMove":0,"result":-1},{"playerMove":0,"result":-1},{"playerMove":0,"result":-1},{"playerMove":0,"result":-1},{"playerMove":0,"result":-1},{"playerMove":0,"result":-1},{"playerMove":0,"result":-1},{"playerMove":0,"result":-1},{"playerMove":1,"result":0},{"playerMove":0,"result":-1},{"playerMove":2,"result":0},{"playerMove":2,"result":1},{"playerMove":1,"result":-1},{"playerMove":0,"result":1},{"playerMove":2,"result":0},{"playerMove":1,"result":1},{"playerMove":0,"result":-1},{"playerMove":2,"result":0},{"playerMove":1,"result":0},{"playerMove":0,"result":-1},{"playerMove":2,"result":-1},{"playerMove":1,"result":-1},{"playerMove":0,"result":-1},{"playerMove":2,"result":-1},{"playerMove":1,"result":-1},{"playerMove":0,"result":-1},{"playerMove":2,"result":-1},{"playerMove":1,"result":-1},{"playerMove":0,"result":-1},{"playerMove":2,"result":-1},{"playerMove":1,"result":-1},{"playerMove":0,"result":-1},{"playerMove":1,"result":1},{"playerMove":1,"result":-1},{"playerMove":0,"result":-1},{"playerMove":1,"result":-1},{"playerMove":0,"result":1},{"playerMove":1,"result":-1},{"playerMove":0,"result":1},{"playerMove":1,"result":1},{"playerMove":0,"result":-1},{"playerMove":2,"result":0},{"playerMove":1,"result":0},{"playerMove":0,"result":-1},{"playerMove":2,"result":0},{"playerMove":1,"result":0},{"playerMove":0,"result":-1},{"playerMove":2,"result":-1},{"playerMove":1,"result":-1},{"playerMove":0,"result":-1},{"playerMove":1,"result":1},{"playerMove":2,"result":0},{"playerMove":0,"result":-1},{"playerMove":1,"result":0},{"playerMove":0,"result":0},{"playerMove":1,"result":-1},{"playerMove":0,"result":1},{"playerMove":1,"result":0},{"playerMove":0,"result":1},{"playerMove":1,"result":-1},{"playerMove":1,"result":0},{"playerMove":0,"result":-1},{"playerMove":1,"result":0},{"playerMove":0,"result":1},{"playerMove":1,"result":0},{"playerMove":0,"result":1},{"playerMove":1,"result":1},{"playerMove":0,"result":1},{"playerMove":1,"result":-1},{"playerMove":0,"result":-1},{"playerMove":1,"result":0},{"playerMove":0,"result":-1},{"playerMove":1,"result":-1},{"playerMove":0,"result":-1},{"playerMove":1,"result":-1},{"playerMove":0,"result":-1},{"playerMove":0,"result":1},{"playerMove":1,"result":0},{"playerMove":0,"result":-1},{"playerMove":1,"result":-1},{"playerMove":1,"result":0},{"playerMove":0,"result":-1},{"playerMove":1,"result":-1},{"playerMove":0,"result":1},{"playerMove":1,"result":0},{"playerMove":0,"result":-1},{"playerMove":1,"result":-1},{"playerMove":0,"result":-1},{"playerMove":1,"result":-1},{"playerMove":0,"result":-1},{"playerMove":1,"result":-1},{"playerMove":0,"result":-1},{"playerMove":1,"result":-1},{"playerMove":0,"result":-1},{"playerMove":0,"result":1},{"playerMove":1,"result":-1},{"playerMove":0,"result":-1},{"playerMove":1,"result":0},{"playerMove":0,"result":-1},{"playerMove":1,"result":0},{"playerMove":0,"result":-1},{"playerMove":0,"result":-1},{"playerMove":2,"result":0},{"playerMove":0,"result":0},{"playerMove":2,"result":1},{"playerMove":0,"result":-1},{"playerMove":2,"result":0},{"playerMove":0,"result":-1},{"playerMove":2,"result":1},{"playerMove":0,"result":1},{"playerMove":2,"result":0},{"playerMove":0,"result":-1},{"playerMove":2,"result":-1},{"playerMove":0,"result":-1},{"playerMove":2,"result":-1},{"playerMove":0,"result":-1},{"playerMove":2,"result":-1},{"playerMove":0,"result":-1},{"playerMove":2,"result":-1},{"playerMove":0,"result":-1},{"playerMove":1,"result":1},{"playerMove":2,"result":0},{"playerMove":1,"result":1},{"playerMove":0,"result":-1},{"playerMove":2,"result":-1},{"playerMove":1,"result":0},{"playerMove":0,"result":-1},{"playerMove":2,"result":-1},{"playerMove":1,"result":-1},{"playerMove":0,"result":1},{"playerMove":2,"result":-1},{"playerMove":1,"result":-1},{"playerMove":0,"result":-1},{"playerMove":2,"result":-1},{"playerMove":1,"result":-1},{"playerMove":0,"result":-1},{"playerMove":2,"result":-1},{"playerMove":1,"result":-1},{"playerMove":0,"result":-1},{"playerMove":2,"result":-1},{"playerMove":1,"result":-1},{"playerMove":0,"result":-1},{"playerMove":1,"result":1},{"playerMove":0,"result":1},{"playerMove":1,"result":-1},{"playerMove":0,"result":-1},{"playerMove":1,"result":1},{"playerMove":0,"result":-1},{"playerMove":1,"result":-1},{"playerMove":0,"result":-1},{"playerMove":1,"result":-1},{"playerMove":0,"result":-1},{"playerMove":1,"result":-1},{"playerMove":0,"result":-1},{"playerMove":2,"result":0},{"playerMove":1,"result":0},{"playerMove":0,"result":-1},{"playerMove":2,"result":1},{"playerMove":1,"result":0},{"playerMove":0,"result":-1},{"playerMove":2,"result":-1},{"playerMove":1,"result":-1},{"playerMove":0,"result":-1},{"playerMove":2,"result":-1},{"playerMove":1,"result":-1},{"playerMove":0,"result":-1},{"playerMove":1,"result":1},{"playerMove":2,"result":0},{"playerMove":0,"result":-1},{"playerMove":1,"result":1},{"playerMove":0,"result":0},{"playerMove":1,"result":1},{"playerMove":0,"result":1},{"playerMove":1,"result":1},{"playerMove":0,"result":-1},{"playerMove":1,"result":-1},{"playerMove":0,"result":-1},{"playerMove":1,"result":-1},{"playerMove":0,"result":-1},{"playerMove":1,"result":-1},{"playerMove":0,"result":-1},{"playerMove":2,"result":0},{"playerMove":1,"result":1},{"playerMove":0,"result":1},{"playerMove":2,"result":0},{"playerMove":1,"result":-1},{"playerMove":0,"result":-1},{"playerMove":2,"result":-1},{"playerMove":1,"result":-1},{"playerMove":0,"result":-1},{"playerMove":1,"result":1},{"playerMove":0,"result":1},{"playerMove":1,"result":-1},{"playerMove":0,"result":-1},{"playerMove":1,"result":-1},{"playerMove":0,"result":-1},{"playerMove":1,"result":-1},{"playerMove":0,"result":-1},{"playerMove":2,"result":0},{"playerMove":2,"result":1},{"playerMove":1,"result":0},{"playerMove":0,"result":-1},{"playerMove":2,"result":-1},{"playerMove":1,"result":1},{"playerMove":0,"result":1},{"playerMove":2,"result":0},{"playerMove":1,"result":1},{"playerMove":0,"result":-1},{"playerMove":2,"result":-1},{"playerMove":1,"result":-1},{"playerMove":0,"result":-1},{"playerMove":2,"result":-1},{"playerMove":1,"result":-1},{"playerMove":0,"result":-1},{"playerMove":2,"result":-1},{"playerMove":1,"result":-1},{"playerMove":0,"result":-1},{"playerMove":2,"result":-1},{"playerMove":1,"result":-1},{"playerMove":0,"result":-1},{"playerMove":1,"result":1},{"playerMove":1,"result":0},{"playerMove":0,"result":-1},{"playerMove":1,"result":-1},{"playerMove":0,"result":1},{"playerMove":1,"result":-1},{"playerMove":0,"result":1},{"playerMove":1,"result":1},{"playerMove":0,"result":1},{"playerMove":1,"result":-1},{"playerMove":0,"result":-1},{"playerMove":1,"result":-1},{"playerMove":0,"result":-1},{"playerMove":1,"result":-1},{"playerMove":0,"result":-1},{"playerMove":1,"result":-1},{"playerMove":0,"result":-1},{"playerMove":2,"result":0}],"stats":{"nOfLoses":322,"nOfRounds":500,"nOfTies":86,"nOfWins":86,"playerWinRate":0.184,"iaWinRate":0.644,"tieRate":0.172}}],"playerName":"Lailton"}